tornado_template_gen
