Metadata-Version: 1.0
Name: tornado-template-gen
Version: 1.1.0
Summary: Generate static HTML files using the Tornado template module
Home-page: https://github.meetmecorp.com/Rejected/transformer
Author: Gavin M. Roy
Author-email: gmr@meetme.com
License: BSD
Platform: UNKNOWN
Classifier: Development Status :: 4 - Beta
Classifier: Environment :: Console
Classifier: Intended Audience :: Developers
Classifier: License :: OSI Approved :: BSD License
Classifier: Operating System :: POSIX
Classifier: Operating System :: POSIX :: Linux
Classifier: Programming Language :: Python :: 2
Classifier: Programming Language :: Python :: 2.6
Classifier: Programming Language :: Python :: 2.7
Classifier: Programming Language :: Python :: 2 :: Only
Classifier: Topic :: Software Development :: Build Tools
